sequoia_diff/__init__.py
sequoia_diff/actions.py
sequoia_diff/loaders.py
sequoia_diff/matching.py
sequoia_diff/models.py
sequoia_diff/py.typed
sequoia_diff/rules.json
sequoia_diff/string_comparisons.py
sequoia_diff-0.0.8.dist-info/LICENSE
sequoia_diff-0.0.8.dist-info/METADATA
sequoia_diff-0.0.8.dist-info/WHEEL
sequoia_diff-0.0.8.dist-info/top_level.txt
sequoia_diff-0.0.8.dist-info/RECORD
