Metadata-Version: 2.1
Name: sequoia_diff
Version: 0.0.8
Author-email: Jonah Sussman <sussmanjonah@gmail.com>
Project-URL: Homepage, https://github.com/JonahSussman/sequoia-diff
Project-URL: Issues, https://github.com/JonahSussman/sequoia-diff/issues
Classifier: Programming Language :: Python :: 3
Requires-Python: >=3.11
License-File: LICENSE
Requires-Dist: tree-sitter ==0.22.3
Requires-Dist: pydantic ==2.8.2
Provides-Extra: dev
Requires-Dist: PyYAML ==6.0.1 ; extra == 'dev'
Requires-Dist: coverage ; extra == 'dev'
Requires-Dist: mypy[mypyc] ; extra == 'dev'
Requires-Dist: types-PyYAML ; extra == 'dev'
Requires-Dist: tree-sitter-java ==0.21.0 ; extra == 'dev'
